{"calibratedrecallk_10":{"TARSItemKNNHermann(K=200,decay_interval=1)":0.0018023943},"calibratedrecallk_20":{"TARSItemKNNHermann(K=200,decay_interval=1)":0.0029958715},"calibratedrecallk_50":{"TARSItemKNNHermann(K=200,decay_interval=1)":0.0080498825},"coveragek_10":{"TARSItemKNNHermann(K=200,decay_interval=1)":0.6034272179},"coveragek_20":{"TARSItemKNNHermann(K=200,decay_interval=1)":0.7506199341},"ndcgk_10":{"TARSItemKNNHermann(K=200,decay_interval=1)":0.000844063},"ndcgk_20":{"TARSItemKNNHermann(K=200,decay_interval=1)":0.0011416038},"ndcgk_50":{"TARSItemKNNHermann(K=200,decay_interval=1)":0.002122587},"precisionk_10":{"TARSItemKNNHermann(K=200,decay_interval=1)":0.0001802394},"precisionk_20":{"TARSItemKNNHermann(K=200,decay_interval=1)":0.0001497936},"precisionk_50":{"TARSItemKNNHermann(K=200,decay_interval=1)":0.0001609976},"reciprocalrankk_10":{"TARSItemKNNHermann(K=200,decay_interval=1)":0.0005588698},"reciprocalrankk_20":{"TARSItemKNNHermann(K=200,decay_interval=1)":0.0006382655},"reciprocalrankk_50":{"TARSItemKNNHermann(K=200,decay_interval=1)":0.0007868042}}